dccpath/__init__.py
dccpath/_blender.py
dccpath/_maya.py
dccpath/_mobu.py
dccpath/py.typed
dccpath-0.1.3.dist-info/METADATA
dccpath-0.1.3.dist-info/WHEEL
dccpath-0.1.3.dist-info/licenses/LICENSE
dccpath-0.1.3.dist-info/RECORD
