Metadata-Version: 2.4
Name: dccpath
Version: 0.1.3
Summary: Utility library for locating common DCC (Digital Content Creation) software executables
Project-URL: Repository, https://git.hwanimation.tech/hwanimationtech/dcc-tools/dccpath
Author-email: Henrik Wilhelmsen <henrik@hwanimation.tech>
Maintainer-email: Henrik Wilhelmsen <henrik@hwanimation.tech>
License-Expression: MPL-2.0
License-File: LICENSE
Keywords: Blender,DCC,Maya,MotionBuilder
Requires-Python: >=3.10
